gittxt/__init__.py
gittxt/__main__.py
gittxt/cli/__init__.py
gittxt/cli/cli_config.py
gittxt/cli/cli_plugin.py
gittxt/cli/cli_reverse.py
gittxt/cli/cli_scan.py
gittxt/cli/cli_utils.py
gittxt/core/__init__.py
gittxt/core/config.py
gittxt/core/constants.py
gittxt/core/logger.py
gittxt/core/output_builder.py
gittxt/core/repository.py
gittxt/core/reverse_engineer.py
gittxt/core/scanner.py
gittxt/formatters/json_formatter.py
gittxt/formatters/markdown_formatter.py
gittxt/formatters/text_formatter.py
gittxt/formatters/zip_formatter.py
gittxt/utils/__init__.py
gittxt/utils/cleanup_utils.py
gittxt/utils/file_utils.py
gittxt/utils/filetype_utils.py
gittxt/utils/formatter_utils.py
gittxt/utils/github_url_utils.py
gittxt/utils/hash_utils.py
gittxt/utils/ignore_utils.py
gittxt/utils/install_utils.py
gittxt/utils/pattern_utils.py
gittxt/utils/repo_url_parser.py
gittxt/utils/subcat_utils.py
gittxt/utils/summary_utils.py
gittxt/utils/tree_utils.py
gittxt-1.7.5.dist-info/LICENSE
gittxt-1.7.5.dist-info/METADATA
gittxt-1.7.5.dist-info/WHEEL
gittxt-1.7.5.dist-info/entry_points.txt
gittxt-1.7.5.dist-info/RECORD
