Metadata-Version: 2.3
Name: gittxt
Version: 1.7.5
Summary: Gittxt: Get text from Git repositories in AI-ready formats
License: MIT
Keywords: llm-dataset,text-extraction,git-repos,ai-preprocessing,cli-tool,nlp,data-pipeline,repo-analysis,source-code,github-scanner,ai-ready
Author: Sandeep Paidipati
Author-email: sandeep.paidipati@gmail.com
Requires-Python: >=3.9,!=3.9.7
Classifier: Development Status :: 4 - Beta
Classifier: Environment :: Console
Classifier: Intended Audience :: Developers
Classifier: Intended Audience :: Science/Research
Classifier: License :: OSI Approved :: MIT License
Classifier: Operating System :: OS Independent
Classifier: Programming Language :: Python
Classifier: Programming Language :: Python :: 3
Classifier: Programming Language :: Python :: 3.9
Classifier: Programming Language :: Python :: 3.10
Classifier: Programming Language :: Python :: 3.11
Classifier: Programming Language :: Python :: 3.12
Classifier: Topic :: Software Development :: Version Control :: Git
Classifier: Topic :: Text Processing :: Linguistic
Classifier: Topic :: Scientific/Engineering :: Artificial Intelligence
Classifier: Topic :: Scientific/Engineering :: Information Analysis
Classifier: Topic :: Utilities
Requires-Dist: aiofiles (>=23.2.1)
Requires-Dist: aiohttp (>=3.9.5)
Requires-Dist: binaryornot (>=0.4.4)
Requires-Dist: click (>=8.1.3)
Requires-Dist: colorama (>=0.4.6)
Requires-Dist: gitpython (>=3.1.40)
Requires-Dist: humanize (>=4.12.2)
Requires-Dist: python-dotenv (>=0.21.1)
Requires-Dist: rich (>=13.9.4)
Requires-Dist: tiktoken (>=0.9.0)
Project-URL: Homepage, https://github.com/sandy-sp/gittxt
Project-URL: Repository, https://github.com/sandy-sp/gittxt
